bwkeepass.py
bundlewrap_keepass-0.1.0.dist-info/LICENSE
bundlewrap_keepass-0.1.0.dist-info/METADATA
bundlewrap_keepass-0.1.0.dist-info/WHEEL
bundlewrap_keepass-0.1.0.dist-info/top_level.txt
bundlewrap_keepass-0.1.0.dist-info/RECORD
