Metadata-Version: 2.1
Name: bundlewrap-keepass
Version: 0.1.0
Summary: Use Keepass passwords in your bundlewrap repo
Home-page: UNKNOWN
Author: Franziska Kunsmann
Author-email: pypi@kunsmann.eu
License: GPLv3
Keywords: configuration,config,management
Platform: UNKNOWN
Classifier: Development Status :: 5 - Production/Stable
Classifier: Intended Audience :: System Administrators
Classifier: License :: OSI Approved :: GNU General Public License v3 (GPLv3)
Classifier: Natural Language :: English
Classifier: Operating System :: POSIX :: Linux
Classifier: Programming Language :: Python
Classifier: Programming Language :: Python :: 3.6
Classifier: Programming Language :: Python :: 3.7
Classifier: Programming Language :: Python :: 3.8
Classifier: Programming Language :: Python :: 3.9
Classifier: Topic :: Software Development :: Libraries :: Python Modules
Classifier: Topic :: System :: Installation/Setup
Classifier: Topic :: System :: Systems Administration
License-File: LICENSE
Requires-Dist: bundlewrap (>=4.0.0)
Requires-Dist: pykeepass (>=4.0.0)
